{
    "job": [
      {
        "T1": [
          {
            "Step1": [
              "detect"
            ]
          }
        ]
      },
      {
        "T2": [
          {
            "Step1": {
              "move arm": 0.3,
              "grasp": "open"
            }
          },
          {
            "Step2": {
              "move arm": 0,
              "grasp": "close"
            }
          },
          {
            "Step3": {
              "move arm": 0.4,
              "grasp": "none"
            }
          }
        ]
      },
      {
        "T3": [
          {
            "Step1": {
              "move arm": 0.2,
              "grasp": "none"
            }
          },
          {
            "Step2": {
              "move arm": 0,
              "grasp": "open"
            }
          },
          {
            "Step3": {
              "move arm": 0.4,
              "grasp": "none"
            }
          }
        ]
      }
    ]
  }